{
    "Ar36": {
        "error": 0.0003811809528525895,
        "error_type": "SEM",
        "filter_outliers_dict": {
            "filter_outliers": true,
            "iterations": 1,
            "std_devs": 2
        },
        "fit": "Parabolic",
        "value": 0.02343293987556071
    },
    "Ar37": {
        "error": 0.0052117589983395884,
        "error_type": "SEM",
        "filter_outliers_dict": {
            "filter_outliers": true,
            "iterations": 1,
            "std_devs": 2
        },
        "fit": "linear",
        "value": 0.11014521927618273
    },
    "Ar38": {
        "error": 0.0032507426981052143,
        "error_type": "SEM",
        "filter_outliers_dict": {
            "filter_outliers": true,
            "iterations": 1,
            "std_devs": 2
        },
        "fit": "linear",
        "value": 0.09901419801185078
    },
    "Ar39": {
        "error": 0.011780335167752133,
        "error_type": "SEM",
        "filter_outliers_dict": {
            "filter_outliers": true,
            "iterations": 1,
            "std_devs": 2
        },
        "fit": "Parabolic",
        "value": 6.032324167080143
    },
    "Ar40": {
        "error": 0.06242869267180038,
        "error_type": "SEM",
        "filter_outliers_dict": {
            "filter_outliers": true,
            "iterations": 1,
            "std_devs": 2
        },
        "fit": "Parabolic",
        "value": 1058.0019561028278
    },
    "Ar41": {
        "error": 0.005581129080497277,
        "error_type": "SEM",
        "filter_outliers_dict": {
            "filter_outliers": true,
            "iterations": 1,
            "std_devs": 2
        },
        "fit": "linear",
        "value": 0.05003512634971401
    }
}